{
  "addresses": [
    {
      "hnrlbls": [
        "1"
      ], 
      "housenumber": "1", 
      "lat": 51.22657350749, 
      "lon": 2.916979368896, 
      "municipality": "Oostende", 
      "pcode": "8400", 
      "source": "manueleAanduidingVanGebouw", 
      "street": "Vindictivelaan"
    }, 
    {
      "busnrs": [
        "0101", 
        "0201", 
        "0301", 
        "0401", 
        "0501", 
        "0601", 
        "0701", 
        "0801", 
        "0901", 
        "1001"
      ], 
      "hnrlbls": [
        "10"
      ], 
      "housenumber": "10", 
      "lat": 51.22785099626, 
      "lon": 2.919919780681, 
      "municipality": "Oostende", 
      "pcode": "8400", 
      "source": "manueleAanduidingVanGebouw", 
      "street": "Vindictivelaan"
    }, 
    {
      "busnrs": [
        "0001", 
        "0002", 
        "0101", 
        "0102", 
        "0201", 
        "0202", 
        "0301", 
        "0302", 
        "0401", 
        "0402", 
        "0501", 
        "0502", 
        "0601", 
        "0602", 
        "0701", 
        "0702", 
        "0801", 
        "0802"
      ], 
      "hnrlbls": [
        "11"
      ], 
      "housenumber": "11", 
      "lat": 51.227860201286, 
      "lon": 2.92000339903, 
      "municipality": "Oostende", 
      "pcode": "8400", 
      "source": "manueleAanduidingVanGebouw", 
      "street": "Vindictivelaan"
    }, 
    {
      "hnrlbls": [
        "13"
      ], 
      "housenumber": "13", 
      "lat": 51.227926019595, 
      "lon": 2.920283279039, 
      "municipality": "Oostende", 
      "pcode": "8400", 
      "source": "manueleAanduidingVanGebouw", 
      "street": "Vindictivelaan"
    }, 
    {
      "busnrs": [
        "0101", 
        "0102", 
        "0103", 
        "0201", 
        "0202", 
        "0203", 
        "0301", 
        "0302", 
        "0303", 
        "0401", 
        "0402", 
        "0403", 
        "0501", 
        "0502", 
        "0503", 
        "0601", 
        "0602", 
        "0603", 
        "0701", 
        "0702", 
        "0703", 
        "0801", 
        "0802", 
        "0803", 
        "0901", 
        "0902", 
        "0903"
      ], 
      "hnrlbls": [
        "14"
      ], 
      "housenumber": "14", 
      "lat": 51.228067545484, 
      "lon": 2.920784459259, 
      "municipality": "Oostende", 
      "pcode": "8400", 
      "source": "manueleAanduidingVanGebouw", 
      "street": "Vindictivelaan"
    }, 
    {
      "busnrs": [
        "0301", 
        "0302", 
        "0401", 
        "0402", 
        "0501", 
        "0502", 
        "0601", 
        "0602", 
        "0701", 
        "0801", 
        "0901"
      ], 
      "hnrlbls": [
        "15"
      ], 
      "housenumber": "15", 
      "lat": 51.228198871826, 
      "lon": 2.921311875032, 
      "municipality": "Oostende", 
      "pcode": "8400", 
      "source": "manueleAanduidingVanGebouw", 
      "street": "Vindictivelaan"
    }, 
    {
      "busnrs": [
        "0101", 
        "0201", 
        "0301", 
        "0401", 
        "0501", 
        "0601", 
        "0701", 
        "0801", 
        "0901"
      ], 
      "hnrlbls": [
        "16"
      ], 
      "housenumber": "16", 
      "lat": 51.228295518007, 
      "lon": 2.92129742088, 
      "municipality": "Oostende", 
      "pcode": "8400", 
      "source": "manueleAanduidingVanGebouw", 
      "street": "Vindictivelaan"
    }, 
    {
      "busnrs": [
        "0101", 
        "0102", 
        "0201", 
        "0202", 
        "0301", 
        "0302", 
        "0401", 
        "0402", 
        "0501", 
        "0502", 
        "0601", 
        "0602", 
        "0701", 
        "0702", 
        "0801", 
        "0802", 
        "0901", 
        "0902"
      ], 
      "hnrlbls": [
        "17"
      ], 
      "housenumber": "17", 
      "lat": 51.228354188517, 
      "lon": 2.921434200976, 
      "municipality": "Oostende", 
      "pcode": "8400", 
      "source": "manueleAanduidingVanGebouw", 
      "street": "Vindictivelaan"
    }, 
    {
      "hnrlbls": [
        "18"
      ], 
      "housenumber": "18", 
      "lat": 51.228291242675, 
      "lon": 2.921646060224, 
      "municipality": "Oostende", 
      "pcode": "8400", 
      "source": "manueleAanduidingVanGebouw", 
      "street": "Vindictivelaan"
    }, 
    {
      "busnrs": [
        "0001", 
        "0101", 
        "0102", 
        "0103", 
        "0104", 
        "0201", 
        "0202", 
        "0203", 
        "0204", 
        "0301", 
        "0302", 
        "0303", 
        "0304", 
        "0401", 
        "0402", 
        "0403", 
        "0404", 
        "0501", 
        "0502", 
        "0503", 
        "0504", 
        "0601", 
        "0602", 
        "0603", 
        "0604", 
        "0701", 
        "0702", 
        "0703", 
        "0704", 
        "0801", 
        "0802", 
        "0803", 
        "0804", 
        "0901", 
        "0902", 
        "0903", 
        "0904"
      ], 
      "hnrlbls": [
        "19"
      ], 
      "housenumber": "19", 
      "lat": 51.228320871868, 
      "lon": 2.921738496021, 
      "municipality": "Oostende", 
      "pcode": "8400", 
      "source": "manueleAanduidingVanGebouw", 
      "street": "Vindictivelaan"
    }, 
    {
      "hnrlbls": [
        "19A"
      ], 
      "housenumber": "19A", 
      "lat": 51.228346412641, 
      "lon": 2.92183478153, 
      "municipality": "Oostende", 
      "pcode": "8400", 
      "source": "manueleAanduidingVanGebouw", 
      "street": "Vindictivelaan"
    }, 
    {
      "hnrlbls": [
        "1A"
      ], 
      "housenumber": "1A", 
      "lat": 51.226873432012, 
      "lon": 2.916511861545, 
      "municipality": "Oostende", 
      "pcode": "8400", 
      "source": "manueleAanduidingVanGebouw", 
      "street": "Vindictivelaan"
    }, 
    {
      "busnrs": [
        "0101", 
        "0102", 
        "0201", 
        "0202", 
        "0301", 
        "0302", 
        "0401", 
        "0402", 
        "0501", 
        "0502"
      ], 
      "hnrlbls": [
        "2"
      ], 
      "housenumber": "2", 
      "lat": 51.226910959863, 
      "lon": 2.916639553757, 
      "municipality": "Oostende", 
      "pcode": "8400", 
      "source": "manueleAanduidingVanGebouw", 
      "street": "Vindictivelaan"
    }, 
    {
      "busnrs": [
        "0101", 
        "0102", 
        "0103", 
        "0201", 
        "0202", 
        "0203", 
        "0301", 
        "0302", 
        "0303", 
        "0304", 
        "0401", 
        "0402", 
        "0403", 
        "0404", 
        "0501", 
        "0502", 
        "0503", 
        "0601", 
        "0602", 
        "0603", 
        "0604", 
        "0701", 
        "0702", 
        "0703", 
        "0704", 
        "0801", 
        "0802", 
        "0803", 
        "0804", 
        "0901", 
        "0902", 
        "0903", 
        "1001"
      ], 
      "hnrlbls": [
        "20"
      ], 
      "housenumber": "20", 
      "lat": 51.228378814639, 
      "lon": 2.921977531924, 
      "municipality": "Oostende", 
      "pcode": "8400", 
      "source": "manueleAanduidingVanGebouw", 
      "street": "Vindictivelaan"
    }, 
    {
      "hnrlbls": [
        "21"
      ], 
      "housenumber": "21", 
      "lat": 51.228465495655, 
      "lon": 2.922331798599, 
      "municipality": "Oostende", 
      "pcode": "8400", 
      "source": "manueleAanduidingVanGebouw", 
      "street": "Vindictivelaan"
    }, 
    {
      "busnrs": [
        "0101", 
        "0102", 
        "0201", 
        "0202", 
        "0301", 
        "0302", 
        "0401", 
        "0402", 
        "0501", 
        "0502", 
        "0601", 
        "0602", 
        "0701", 
        "0702", 
        "0801", 
        "0802", 
        "0901", 
        "0902"
      ], 
      "hnrlbls": [
        "22"
      ], 
      "housenumber": "22", 
      "lat": 51.228618068155, 
      "lon": 2.922428297469, 
      "municipality": "Oostende", 
      "pcode": "8400", 
      "source": "manueleAanduidingVanGebouw", 
      "street": "Vindictivelaan"
    }, 
    {
      "busnrs": [
        "0801", 
        "1", 
        "2", 
        "3", 
        "4", 
        "7", 
        "8", 
        "9"
      ], 
      "hnrlbls": [
        "23"
      ], 
      "housenumber": "23", 
      "lat": 51.228603794464, 
      "lon": 2.92254028016, 
      "municipality": "Oostende", 
      "pcode": "8400", 
      "source": "afgeleidVanGebouw", 
      "street": "Vindictivelaan"
    }, 
    {
      "busnrs": [
        "0001", 
        "0101", 
        "0102", 
        "0201", 
        "0202", 
        "0301", 
        "0302", 
        "0401", 
        "0402", 
        "0501", 
        "0502", 
        "0601", 
        "0602", 
        "0701", 
        "0702", 
        "0801", 
        "0802", 
        "0901", 
        "0902", 
        "1001"
      ], 
      "hnrlbls": [
        "24"
      ], 
      "housenumber": "24", 
      "lat": 51.228638666072, 
      "lon": 2.922642434241, 
      "municipality": "Oostende", 
      "pcode": "8400", 
      "source": "manueleAanduidingVanGebouw", 
      "street": "Vindictivelaan"
    }, 
    {
      "hnrlbls": [
        "25"
      ], 
      "housenumber": "25", 
      "lat": 51.228686398508, 
      "lon": 2.922870048314, 
      "municipality": "Oostende", 
      "pcode": "8400", 
      "source": "manueleAanduidingVanGebouw", 
      "street": "Vindictivelaan"
    }, 
    {
      "hnrlbls": [
        "25C"
      ], 
      "housenumber": "25C", 
      "lat": 51.228788050452, 
      "lon": 2.923095991428, 
      "municipality": "Oostende", 
      "pcode": "8400", 
      "source": "manueleAanduidingVanGebouw", 
      "street": "Vindictivelaan"
    }, 
    {
      "hnrlbls": [
        "26"
      ], 
      "housenumber": "26", 
      "lat": 51.228872401473, 
      "lon": 2.92323040416, 
      "municipality": "Oostende", 
      "pcode": "8400", 
      "source": "manueleAanduidingVanGebouw", 
      "street": "Vindictivelaan"
    }, 
    {
      "busnrs": [
        "0101", 
        "0102", 
        "0103", 
        "0201", 
        "0202", 
        "0203", 
        "0301", 
        "0302", 
        "0303", 
        "0401", 
        "0402", 
        "0403", 
        "0501", 
        "0502", 
        "0503", 
        "0601", 
        "0602", 
        "0603"
      ], 
      "hnrlbls": [
        "27"
      ], 
      "housenumber": "27", 
      "lat": 51.228962707017, 
      "lon": 2.923263544446, 
      "municipality": "Oostende", 
      "pcode": "8400", 
      "source": "manueleAanduidingVanGebouw", 
      "street": "Vindictivelaan"
    }, 
    {
      "busnrs": [
        "0101", 
        "0201", 
        "0301"
      ], 
      "hnrlbls": [
        "29"
      ], 
      "housenumber": "29", 
      "lat": 51.22901203812, 
      "lon": 2.923246837843, 
      "municipality": "Oostende", 
      "pcode": "8400", 
      "source": "manueleAanduidingVanGebouw", 
      "street": "Vindictivelaan"
    }, 
    {
      "hnrlbls": [
        "3"
      ], 
      "housenumber": "3", 
      "lat": 51.226948663247, 
      "lon": 2.916781558579, 
      "municipality": "Oostende", 
      "pcode": "8400", 
      "source": "manueleAanduidingVanGebouw", 
      "street": "Vindictivelaan"
    }, 
    {
      "busnrs": [
        "0101", 
        "0201", 
        "0301", 
        "0401"
      ], 
      "hnrlbls": [
        "30"
      ], 
      "housenumber": "30", 
      "lat": 51.229058290193, 
      "lon": 2.923294516694, 
      "municipality": "Oostende", 
      "pcode": "8400", 
      "source": "manueleAanduidingVanGebouw", 
      "street": "Vindictivelaan"
    }, 
    {
      "hnrlbls": [
        "31"
      ], 
      "housenumber": "31", 
      "lat": 51.229114193519, 
      "lon": 2.923300659194, 
      "municipality": "Oostende", 
      "pcode": "8400", 
      "source": "manueleAanduidingVanGebouw", 
      "street": "Vindictivelaan"
    }, 
    {
      "busnrs": [
        "0101", 
        "0102", 
        "0201", 
        "0202", 
        "0301", 
        "0302", 
        "0401", 
        "0402", 
        "0501", 
        "0502", 
        "0601", 
        "0602"
      ], 
      "hnrlbls": [
        "32"
      ], 
      "housenumber": "32", 
      "lat": 51.22916909831, 
      "lon": 2.923357520257, 
      "municipality": "Oostende", 
      "pcode": "8400", 
      "source": "manueleAanduidingVanGebouw", 
      "street": "Vindictivelaan"
    }, 
    {
      "busnrs": [
        "0101", 
        "0201", 
        "0301", 
        "0401", 
        "0501", 
        "0601"
      ], 
      "hnrlbls": [
        "33"
      ], 
      "housenumber": "33", 
      "lat": 51.229207062609, 
      "lon": 2.923374384994, 
      "municipality": "Oostende", 
      "pcode": "8400", 
      "source": "manueleAanduidingVanGebouw", 
      "street": "Vindictivelaan"
    }, 
    {
      "hnrlbls": [
        "34"
      ], 
      "housenumber": "34", 
      "lat": 51.229313936772, 
      "lon": 2.923277286007, 
      "municipality": "Oostende", 
      "pcode": "8400", 
      "source": "afgeleidVanGebouw", 
      "street": "Vindictivelaan"
    }, 
    {
      "hnrlbls": [
        "35"
      ], 
      "housenumber": "35", 
      "lat": 51.229436900159, 
      "lon": 2.923430120402, 
      "municipality": "Oostende", 
      "pcode": "8400", 
      "source": "afgeleidVanGebouw", 
      "street": "Vindictivelaan"
    }, 
    {
      "busnrs": [
        "0001", 
        "0201", 
        "0202", 
        "0203", 
        "0301", 
        "0302", 
        "0303", 
        "0401", 
        "0402", 
        "0403", 
        "0501", 
        "0502", 
        "0503", 
        "0601", 
        "0602", 
        "0603", 
        "0701", 
        "0702", 
        "0703", 
        "0801", 
        "0802", 
        "0803", 
        "0901", 
        "0902", 
        "0903"
      ], 
      "hnrlbls": [
        "5"
      ], 
      "housenumber": "5", 
      "lat": 51.227538248552, 
      "lon": 2.918864520199, 
      "municipality": "Oostende", 
      "pcode": "8400", 
      "source": "manueleAanduidingVanGebouw", 
      "street": "Vindictivelaan"
    }, 
    {
      "busnrs": [
        "0101", 
        "0201", 
        "0301", 
        "0401", 
        "0501", 
        "0601"
      ], 
      "hnrlbls": [
        "6"
      ], 
      "housenumber": "6", 
      "lat": 51.227616849047, 
      "lon": 2.919006116435, 
      "municipality": "Oostende", 
      "pcode": "8400", 
      "source": "manueleAanduidingVanGebouw", 
      "street": "Vindictivelaan"
    }, 
    {
      "busnrs": [
        "0101", 
        "0201", 
        "0301", 
        "0401", 
        "0501", 
        "0601", 
        "0701", 
        "0801", 
        "0901"
      ], 
      "hnrlbls": [
        "7"
      ], 
      "housenumber": "7", 
      "lat": 51.227617440806, 
      "lon": 2.919135103855, 
      "municipality": "Oostende", 
      "pcode": "8400", 
      "source": "manueleAanduidingVanGebouw", 
      "street": "Vindictivelaan"
    }, 
    {
      "busnrs": [
        "0201", 
        "0301", 
        "0401", 
        "0601", 
        "0701", 
        "0801", 
        "0901"
      ], 
      "hnrlbls": [
        "8"
      ], 
      "housenumber": "8", 
      "lat": 51.227631948561, 
      "lon": 2.919247908887, 
      "municipality": "Oostende", 
      "pcode": "8400", 
      "source": "manueleAanduidingVanGebouw", 
      "street": "Vindictivelaan"
    }, 
    {
      "hnrlbls": [
        "9"
      ], 
      "housenumber": "9", 
      "lat": 51.227729128963, 
      "lon": 2.919577927592, 
      "municipality": "Oostende", 
      "pcode": "8400", 
      "source": "manueleAanduidingVanGebouw", 
      "street": "Vindictivelaan"
    }
  ]
}