{
  "addresses": [
    {
      "hnrlbls": [
        "13"
      ], 
      "housenumber": "13", 
      "lat": 50.907326049049, 
      "lon": 4.196731119579, 
      "municipality": "Asse", 
      "pcode": "1730", 
      "source": "afgeleidVanGebouw", 
      "street": "Langevijver"
    }, 
    {
      "hnrlbls": [
        "15"
      ], 
      "housenumber": "15", 
      "lat": 50.907283780757, 
      "lon": 4.196472369577, 
      "municipality": "Asse", 
      "pcode": "1730", 
      "source": "afgeleidVanGebouw", 
      "street": "Langevijver"
    }, 
    {
      "hnrlbls": [
        "19"
      ], 
      "housenumber": "19", 
      "lat": 50.906994607166, 
      "lon": 4.196852041434, 
      "municipality": "Asse", 
      "pcode": "1730", 
      "source": "manueleAanduidingVanLot", 
      "street": "Langevijver"
    }, 
    {
      "hnrlbls": [
        "22"
      ], 
      "housenumber": "22", 
      "lat": 50.907389295682, 
      "lon": 4.195599299708, 
      "municipality": "Asse", 
      "pcode": "1730", 
      "source": "manueleAanduidingVanPerceel", 
      "street": "Langevijver"
    }, 
    {
      "hnrlbls": [
        "23"
      ], 
      "housenumber": "23", 
      "lat": 50.906752810453, 
      "lon": 4.197110971512, 
      "municipality": "Asse", 
      "pcode": "1730", 
      "source": "afgeleidVanGebouw", 
      "street": "Langevijver"
    }, 
    {
      "hnrlbls": [
        "25"
      ], 
      "housenumber": "25", 
      "lat": 50.906658961858, 
      "lon": 4.196741231526, 
      "municipality": "Asse", 
      "pcode": "1730", 
      "source": "afgeleidVanGebouw", 
      "street": "Langevijver"
    }, 
    {
      "hnrlbls": [
        "31"
      ], 
      "housenumber": "31", 
      "lat": 50.906793776377, 
      "lon": 4.195985503375, 
      "municipality": "Asse", 
      "pcode": "1730", 
      "source": "afgeleidVanGebouw", 
      "street": "Langevijver"
    }, 
    {
      "hnrlbls": [
        "32"
      ], 
      "housenumber": "32", 
      "lat": 50.907240314972, 
      "lon": 4.194543757405, 
      "municipality": "Asse", 
      "pcode": "1730", 
      "source": "manueleAanduidingVanLot", 
      "street": "Langevijver"
    }, 
    {
      "hnrlbls": [
        "33"
      ], 
      "housenumber": "33", 
      "lat": 50.90694825958, 
      "lon": 4.195832666693, 
      "municipality": "Asse", 
      "pcode": "1730", 
      "source": "afgeleidVanGebouw", 
      "street": "Langevijver"
    }, 
    {
      "hnrlbls": [
        "35"
      ], 
      "housenumber": "35", 
      "lat": 50.907109472932, 
      "lon": 4.195733120459, 
      "municipality": "Asse", 
      "pcode": "1730", 
      "source": "afgeleidVanGebouw", 
      "street": "Langevijver"
    }, 
    {
      "hnrlbls": [
        "37"
      ], 
      "housenumber": "37", 
      "lat": 50.907032539535, 
      "lon": 4.195254411199, 
      "municipality": "Asse", 
      "pcode": "1730", 
      "source": "afgeleidVanGebouw", 
      "street": "Langevijver"
    }, 
    {
      "hnrlbls": [
        "39"
      ], 
      "housenumber": "39", 
      "lat": 50.907006055684, 
      "lon": 4.194972857762, 
      "municipality": "Asse", 
      "pcode": "1730", 
      "source": "afgeleidVanGebouw", 
      "street": "Langevijver"
    }, 
    {
      "hnrlbls": [
        "43"
      ], 
      "housenumber": "43", 
      "lat": 50.906944648178, 
      "lon": 4.194418029256, 
      "municipality": "Asse", 
      "pcode": "1730", 
      "source": "afgeleidVanGebouw", 
      "street": "Langevijver"
    }, 
    {
      "hnrlbls": [
        "45"
      ], 
      "housenumber": "45", 
      "lat": 50.906901037754, 
      "lon": 4.194166965885, 
      "municipality": "Asse", 
      "pcode": "1730", 
      "source": "afgeleidVanGebouw", 
      "street": "Langevijver"
    }
  ]
}