{
  "addresses": [
    {
      "hnrlbls": [
        "10"
      ], 
      "housenumber": "10", 
      "lat": 51.174379204895, 
      "lon": 3.300759559921, 
      "municipality": "Beernem", 
      "pcode": "8730", 
      "source": "afgeleidVanGebouw", 
      "street": "Veldkapellestraat"
    }, 
    {
      "hnrlbls": [
        "11"
      ], 
      "housenumber": "11", 
      "lat": 51.174301750894, 
      "lon": 3.30051479104, 
      "municipality": "Beernem", 
      "pcode": "8730", 
      "source": "afgeleidVanGebouw", 
      "street": "Veldkapellestraat"
    }, 
    {
      "hnrlbls": [
        "2"
      ], 
      "housenumber": "2", 
      "lat": 51.175019913366, 
      "lon": 3.302485158595, 
      "municipality": "Beernem", 
      "pcode": "8730", 
      "source": "afgeleidVanGebouw", 
      "street": "Veldkapellestraat"
    }, 
    {
      "hnrlbls": [
        "3"
      ], 
      "housenumber": "3", 
      "lat": 51.174896913381, 
      "lon": 3.302323080378, 
      "municipality": "Beernem", 
      "pcode": "8730", 
      "source": "afgeleidVanGebouw", 
      "street": "Veldkapellestraat"
    }, 
    {
      "hnrlbls": [
        "4"
      ], 
      "housenumber": "4", 
      "lat": 51.174824264179, 
      "lon": 3.301873268554, 
      "municipality": "Beernem", 
      "pcode": "8730", 
      "source": "afgeleidVanGebouw", 
      "street": "Veldkapellestraat"
    }, 
    {
      "hnrlbls": [
        "5"
      ], 
      "housenumber": "5", 
      "lat": 51.174779968597, 
      "lon": 3.301696523838, 
      "municipality": "Beernem", 
      "pcode": "8730", 
      "source": "afgeleidVanGebouw", 
      "street": "Veldkapellestraat"
    }, 
    {
      "hnrlbls": [
        "6"
      ], 
      "housenumber": "6", 
      "lat": 51.174677406045, 
      "lon": 3.301368809757, 
      "municipality": "Beernem", 
      "pcode": "8730", 
      "source": "afgeleidVanGebouw", 
      "street": "Veldkapellestraat"
    }, 
    {
      "hnrlbls": [
        "7"
      ], 
      "housenumber": "7", 
      "lat": 51.174644132895, 
      "lon": 3.301128605568, 
      "municipality": "Beernem", 
      "pcode": "8730", 
      "source": "afgeleidVanGebouw", 
      "street": "Veldkapellestraat"
    }, 
    {
      "hnrlbls": [
        "8"
      ], 
      "housenumber": "8", 
      "lat": 51.174585820063, 
      "lon": 3.301012388044, 
      "municipality": "Beernem", 
      "pcode": "8730", 
      "source": "afgeleidVanGebouw", 
      "street": "Veldkapellestraat"
    }, 
    {
      "hnrlbls": [
        "9"
      ], 
      "housenumber": "9", 
      "lat": 51.174412040386, 
      "lon": 3.300871640006, 
      "municipality": "Beernem", 
      "pcode": "8730", 
      "source": "afgeleidVanGebouw", 
      "street": "Veldkapellestraat"
    }
  ]
}