{
  "addresses": [
    {
      "hnrlbls": [
        "10"
      ], 
      "housenumber": "10", 
      "lat": 51.202104725542, 
      "lon": 4.424663998749, 
      "municipality": "Antwerpen", 
      "pcode": "2018", 
      "source": "afgeleidVanGebouw", 
      "street": "Henri La Fontainestraat"
    }, 
    {
      "hnrlbls": [
        "12"
      ], 
      "housenumber": "12", 
      "lat": 51.202147498909, 
      "lon": 4.424688373454, 
      "municipality": "Antwerpen", 
      "pcode": "2018", 
      "source": "afgeleidVanGebouw", 
      "street": "Henri La Fontainestraat"
    }, 
    {
      "hnrlbls": [
        "5-17"
      ], 
      "housenumber": "13", 
      "lat": 51.202152287963, 
      "lon": 4.424259010254, 
      "municipality": "Antwerpen", 
      "pcode": "2018", 
      "source": "afgeleidVanPerceelGrb", 
      "street": "Henri La Fontainestraat"
    }, 
    {
      "hnrlbls": [
        "14"
      ], 
      "housenumber": "14", 
      "lat": 51.20219296613, 
      "lon": 4.424718331417, 
      "municipality": "Antwerpen", 
      "pcode": "2018", 
      "source": "afgeleidVanGebouw", 
      "street": "Henri La Fontainestraat"
    }, 
    {
      "hnrlbls": [
        "5-17"
      ], 
      "housenumber": "15", 
      "lat": 51.202152287963, 
      "lon": 4.424259010254, 
      "municipality": "Antwerpen", 
      "pcode": "2018", 
      "source": "afgeleidVanPerceelGrb", 
      "street": "Henri La Fontainestraat"
    }, 
    {
      "hnrlbls": [
        "16"
      ], 
      "housenumber": "16", 
      "lat": 51.202231965297, 
      "lon": 4.424740698574, 
      "municipality": "Antwerpen", 
      "pcode": "2018", 
      "source": "afgeleidVanGebouw", 
      "street": "Henri La Fontainestraat"
    }, 
    {
      "hnrlbls": [
        "5-17"
      ], 
      "housenumber": "17", 
      "lat": 51.202152287963, 
      "lon": 4.424259010254, 
      "municipality": "Antwerpen", 
      "pcode": "2018", 
      "source": "afgeleidVanPerceelGrb", 
      "street": "Henri La Fontainestraat"
    }, 
    {
      "hnrlbls": [
        "18"
      ], 
      "housenumber": "18", 
      "lat": 51.202271324477, 
      "lon": 4.424762064676, 
      "municipality": "Antwerpen", 
      "pcode": "2018", 
      "source": "afgeleidVanGebouw", 
      "street": "Henri La Fontainestraat"
    }, 
    {
      "hnrlbls": [
        "20"
      ], 
      "housenumber": "20", 
      "lat": 51.202314546763, 
      "lon": 4.424787441635, 
      "municipality": "Antwerpen", 
      "pcode": "2018", 
      "source": "afgeleidVanGebouw", 
      "street": "Henri La Fontainestraat"
    }, 
    {
      "hnrlbls": [
        "22"
      ], 
      "housenumber": "22", 
      "lat": 51.202357949017, 
      "lon": 4.424812389632, 
      "municipality": "Antwerpen", 
      "pcode": "2018", 
      "source": "afgeleidVanGebouw", 
      "street": "Henri La Fontainestraat"
    }, 
    {
      "hnrlbls": [
        "24"
      ], 
      "housenumber": "24", 
      "lat": 51.202391378281, 
      "lon": 4.424828597897, 
      "municipality": "Antwerpen", 
      "pcode": "2018", 
      "source": "afgeleidVanGebouw", 
      "street": "Henri La Fontainestraat"
    }, 
    {
      "hnrlbls": [
        "26"
      ], 
      "housenumber": "26", 
      "lat": 51.202431455212, 
      "lon": 4.424852683467, 
      "municipality": "Antwerpen", 
      "pcode": "2018", 
      "source": "afgeleidVanGebouw", 
      "street": "Henri La Fontainestraat"
    }, 
    {
      "apptnrs": [
        "001", 
        "101", 
        "102", 
        "103", 
        "201", 
        "202", 
        "203"
      ], 
      "hnrlbls": [
        "28-28A"
      ], 
      "housenumber": "28", 
      "lat": 51.202505860786, 
      "lon": 4.424891833914, 
      "municipality": "Antwerpen", 
      "pcode": "2018", 
      "source": "afgeleidVanGebouw", 
      "street": "Henri La Fontainestraat"
    }, 
    {
      "hnrlbls": [
        "28-28A"
      ], 
      "housenumber": "28A", 
      "lat": 51.202505860786, 
      "lon": 4.424891833914, 
      "municipality": "Antwerpen", 
      "pcode": "2018", 
      "source": "afgeleidVanGebouw", 
      "street": "Henri La Fontainestraat"
    }, 
    {
      "hnrlbls": [
        "30"
      ], 
      "housenumber": "30", 
      "lat": 51.202588203687, 
      "lon": 4.425060478533, 
      "municipality": "Antwerpen", 
      "pcode": "2018", 
      "source": "afgeleidVanGebouw", 
      "street": "Henri La Fontainestraat"
    }, 
    {
      "hnrlbls": [
        "32"
      ], 
      "housenumber": "32", 
      "lat": 51.202570011809, 
      "lon": 4.425133425366, 
      "municipality": "Antwerpen", 
      "pcode": "2018", 
      "source": "afgeleidVanGebouw", 
      "street": "Henri La Fontainestraat"
    }, 
    {
      "hnrlbls": [
        "34"
      ], 
      "housenumber": "34", 
      "lat": 51.202553977874, 
      "lon": 4.425204800944, 
      "municipality": "Antwerpen", 
      "pcode": "2018", 
      "source": "afgeleidVanGebouw", 
      "street": "Henri La Fontainestraat"
    }, 
    {
      "hnrlbls": [
        "36"
      ], 
      "housenumber": "36", 
      "lat": 51.202537405421, 
      "lon": 4.425274458895, 
      "municipality": "Antwerpen", 
      "pcode": "2018", 
      "source": "afgeleidVanGebouw", 
      "street": "Henri La Fontainestraat"
    }, 
    {
      "apptnrs": [
        "001", 
        "101", 
        "102", 
        "201", 
        "202"
      ], 
      "hnrlbls": [
        "4"
      ], 
      "housenumber": "4", 
      "lat": 51.201920328153, 
      "lon": 4.424568487305, 
      "municipality": "Antwerpen", 
      "pcode": "2018", 
      "source": "afgeleidVanGebouw", 
      "street": "Henri La Fontainestraat"
    }, 
    {
      "hnrlbls": [
        "40"
      ], 
      "housenumber": "40", 
      "lat": 51.202759784702, 
      "lon": 4.424891570979, 
      "municipality": "Antwerpen", 
      "pcode": "2018", 
      "source": "afgeleidVanGebouw", 
      "street": "Henri La Fontainestraat"
    }, 
    {
      "apptnrs": [
        "001", 
        "002", 
        "101", 
        "102", 
        "201", 
        "202", 
        "301", 
        "302", 
        "401", 
        "402"
      ], 
      "hnrlbls": [
        "30-43"
      ], 
      "housenumber": "41", 
      "lat": 51.203126308667, 
      "lon": 4.42475666547, 
      "municipality": "Antwerpen", 
      "pcode": "2018", 
      "source": "afgeleidVanGebouw", 
      "street": "Henri La Fontainestraat"
    }, 
    {
      "apptnrs": [
        "001", 
        "101"
      ], 
      "hnrlbls": [
        "42"
      ], 
      "housenumber": "42", 
      "lat": 51.202804804022, 
      "lon": 4.42491823821, 
      "municipality": "Antwerpen", 
      "pcode": "2018", 
      "source": "afgeleidVanGebouw", 
      "street": "Henri La Fontainestraat"
    }, 
    {
      "hnrlbls": [
        "30-43"
      ], 
      "housenumber": "43", 
      "lat": 51.203126308667, 
      "lon": 4.42475666547, 
      "municipality": "Antwerpen", 
      "pcode": "2018", 
      "source": "afgeleidVanGebouw", 
      "street": "Henri La Fontainestraat"
    }, 
    {
      "hnrlbls": [
        "44"
      ], 
      "housenumber": "44", 
      "lat": 51.202851885719, 
      "lon": 4.424955209584, 
      "municipality": "Antwerpen", 
      "pcode": "2018", 
      "source": "afgeleidVanGebouw", 
      "street": "Henri La Fontainestraat"
    }, 
    {
      "hnrlbls": [
        "34-47"
      ], 
      "housenumber": "45", 
      "lat": 51.20311058122, 
      "lon": 4.424751781693, 
      "municipality": "Antwerpen", 
      "pcode": "2018", 
      "source": "afgeleidVanPerceelGrb", 
      "street": "Henri La Fontainestraat"
    }, 
    {
      "hnrlbls": [
        "46"
      ], 
      "housenumber": "46", 
      "lat": 51.202893046467, 
      "lon": 4.424968422927, 
      "municipality": "Antwerpen", 
      "pcode": "2018", 
      "source": "afgeleidVanGebouw", 
      "street": "Henri La Fontainestraat"
    }, 
    {
      "hnrlbls": [
        "34-47"
      ], 
      "housenumber": "47", 
      "lat": 51.20311058122, 
      "lon": 4.424751781693, 
      "municipality": "Antwerpen", 
      "pcode": "2018", 
      "source": "afgeleidVanPerceelGrb", 
      "street": "Henri La Fontainestraat"
    }, 
    {
      "hnrlbls": [
        "48"
      ], 
      "housenumber": "48", 
      "lat": 51.202936538558, 
      "lon": 4.424993371511, 
      "municipality": "Antwerpen", 
      "pcode": "2018", 
      "source": "afgeleidVanGebouw", 
      "street": "Henri La Fontainestraat"
    }, 
    {
      "hnrlbls": [
        "5-17"
      ], 
      "housenumber": "5", 
      "lat": 51.202152287963, 
      "lon": 4.424259010254, 
      "municipality": "Antwerpen", 
      "pcode": "2018", 
      "source": "afgeleidVanPerceelGrb", 
      "street": "Henri La Fontainestraat"
    }, 
    {
      "hnrlbls": [
        "50"
      ], 
      "housenumber": "50", 
      "lat": 51.202980120321, 
      "lon": 4.425018749485, 
      "municipality": "Antwerpen", 
      "pcode": "2018", 
      "source": "afgeleidVanGebouw", 
      "street": "Henri La Fontainestraat"
    }, 
    {
      "hnrlbls": [
        "52"
      ], 
      "housenumber": "52", 
      "lat": 51.202942132603, 
      "lon": 4.425321598667, 
      "municipality": "Antwerpen", 
      "pcode": "2018", 
      "source": "afgeleidVanPerceelGrb", 
      "street": "Henri La Fontainestraat"
    }, 
    {
      "hnrlbls": [
        "54"
      ], 
      "housenumber": "54", 
      "lat": 51.203023882192, 
      "lon": 4.425043412336, 
      "municipality": "Antwerpen", 
      "pcode": "2018", 
      "source": "afgeleidVanGebouw", 
      "street": "Henri La Fontainestraat"
    }, 
    {
      "hnrlbls": [
        "56"
      ], 
      "housenumber": "56", 
      "lat": 51.203067464011, 
      "lon": 4.425068647327, 
      "municipality": "Antwerpen", 
      "pcode": "2018", 
      "source": "afgeleidVanGebouw", 
      "street": "Henri La Fontainestraat"
    }, 
    {
      "hnrlbls": [
        "58"
      ], 
      "housenumber": "58", 
      "lat": 51.20311777977, 
      "lon": 4.425109199973, 
      "municipality": "Antwerpen", 
      "pcode": "2018", 
      "source": "afgeleidVanGebouw", 
      "street": "Henri La Fontainestraat"
    }, 
    {
      "hnrlbls": [
        "6"
      ], 
      "housenumber": "6", 
      "lat": 51.202015671447, 
      "lon": 4.424619108243, 
      "municipality": "Antwerpen", 
      "pcode": "2018", 
      "source": "afgeleidVanGebouw", 
      "street": "Henri La Fontainestraat"
    }, 
    {
      "hnrlbls": [
        "29-60"
      ], 
      "housenumber": "60", 
      "lat": 51.203247472816, 
      "lon": 4.425130534237, 
      "municipality": "Antwerpen", 
      "pcode": "2018", 
      "source": "afgeleidVanGebouw", 
      "street": "Henri La Fontainestraat"
    }, 
    {
      "hnrlbls": [
        "8"
      ], 
      "housenumber": "8", 
      "lat": 51.2020604229, 
      "lon": 4.424642197584, 
      "municipality": "Antwerpen", 
      "pcode": "2018", 
      "source": "afgeleidVanGebouw", 
      "street": "Henri La Fontainestraat"
    }
  ]
}