{
  "addresses": [
    {
      "hnrlbls": [
        "1"
      ], 
      "housenumber": "1", 
      "lat": 51.316438407576, 
      "lon": 4.979148471129, 
      "municipality": "Oud-Turnhout", 
      "pcode": "2360", 
      "source": "afgeleidVanGebouw", 
      "street": "Kuileinde"
    }, 
    {
      "hnrlbls": [
        "10"
      ], 
      "housenumber": "10", 
      "lat": 51.316628489863, 
      "lon": 4.979013129296, 
      "municipality": "Oud-Turnhout", 
      "pcode": "2360", 
      "source": "afgeleidVanGebouw", 
      "street": "Kuileinde"
    }, 
    {
      "hnrlbls": [
        "11"
      ], 
      "housenumber": "11", 
      "lat": 51.3165596061, 
      "lon": 4.97933322541, 
      "municipality": "Oud-Turnhout", 
      "pcode": "2360", 
      "source": "afgeleidVanGebouw", 
      "street": "Kuileinde"
    }, 
    {
      "hnrlbls": [
        "12"
      ], 
      "housenumber": "12", 
      "lat": 51.316647656372, 
      "lon": 4.979096141323, 
      "municipality": "Oud-Turnhout", 
      "pcode": "2360", 
      "source": "afgeleidVanGebouw", 
      "street": "Kuileinde"
    }, 
    {
      "hnrlbls": [
        "13"
      ], 
      "housenumber": "13", 
      "lat": 51.316572084532, 
      "lon": 4.979388467209, 
      "municipality": "Oud-Turnhout", 
      "pcode": "2360", 
      "source": "afgeleidVanGebouw", 
      "street": "Kuileinde"
    }, 
    {
      "hnrlbls": [
        "14"
      ], 
      "housenumber": "14", 
      "lat": 51.316682594992, 
      "lon": 4.979136044023, 
      "municipality": "Oud-Turnhout", 
      "pcode": "2360", 
      "source": "afgeleidVanGebouw", 
      "street": "Kuileinde"
    }, 
    {
      "hnrlbls": [
        "15"
      ], 
      "housenumber": "15", 
      "lat": 51.316592907544, 
      "lon": 4.979411689914, 
      "municipality": "Oud-Turnhout", 
      "pcode": "2360", 
      "source": "afgeleidVanGebouw", 
      "street": "Kuileinde"
    }, 
    {
      "hnrlbls": [
        "16"
      ], 
      "housenumber": "16", 
      "lat": 51.316701699285, 
      "lon": 4.979196249639, 
      "municipality": "Oud-Turnhout", 
      "pcode": "2360", 
      "source": "afgeleidVanGebouw", 
      "street": "Kuileinde"
    }, 
    {
      "hnrlbls": [
        "17"
      ], 
      "housenumber": "17", 
      "lat": 51.316605158493, 
      "lon": 4.979458753158, 
      "municipality": "Oud-Turnhout", 
      "pcode": "2360", 
      "source": "afgeleidVanGebouw", 
      "street": "Kuileinde"
    }, 
    {
      "hnrlbls": [
        "18"
      ], 
      "housenumber": "18", 
      "lat": 51.316726716974, 
      "lon": 4.979225264715, 
      "municipality": "Oud-Turnhout", 
      "pcode": "2360", 
      "source": "afgeleidVanGebouw", 
      "street": "Kuileinde"
    }, 
    {
      "hnrlbls": [
        "19"
      ], 
      "housenumber": "19", 
      "lat": 51.316626583987, 
      "lon": 4.979487147384, 
      "municipality": "Oud-Turnhout", 
      "pcode": "2360", 
      "source": "afgeleidVanGebouw", 
      "street": "Kuileinde"
    }, 
    {
      "hnrlbls": [
        "2"
      ], 
      "housenumber": "2", 
      "lat": 51.316494582234, 
      "lon": 4.978817738241, 
      "municipality": "Oud-Turnhout", 
      "pcode": "2360", 
      "source": "afgeleidVanGebouw", 
      "street": "Kuileinde"
    }, 
    {
      "hnrlbls": [
        "3"
      ], 
      "housenumber": "3", 
      "lat": 51.31646469318, 
      "lon": 4.979175638057, 
      "municipality": "Oud-Turnhout", 
      "pcode": "2360", 
      "source": "afgeleidVanGebouw", 
      "street": "Kuileinde"
    }, 
    {
      "hnrlbls": [
        "4"
      ], 
      "housenumber": "4", 
      "lat": 51.316530960466, 
      "lon": 4.978857372634, 
      "municipality": "Oud-Turnhout", 
      "pcode": "2360", 
      "source": "afgeleidVanGebouw", 
      "street": "Kuileinde"
    }, 
    {
      "hnrlbls": [
        "5"
      ], 
      "housenumber": "5", 
      "lat": 51.316487113676, 
      "lon": 4.979220252914, 
      "municipality": "Oud-Turnhout", 
      "pcode": "2360", 
      "source": "afgeleidVanGebouw", 
      "street": "Kuileinde"
    }, 
    {
      "hnrlbls": [
        "6"
      ], 
      "housenumber": "6", 
      "lat": 51.316568508568, 
      "lon": 4.978896735583, 
      "municipality": "Oud-Turnhout", 
      "pcode": "2360", 
      "source": "afgeleidVanGebouw", 
      "street": "Kuileinde"
    }, 
    {
      "hnrlbls": [
        "7"
      ], 
      "housenumber": "7", 
      "lat": 51.316517059818, 
      "lon": 4.979252201243, 
      "municipality": "Oud-Turnhout", 
      "pcode": "2360", 
      "source": "afgeleidVanGebouw", 
      "street": "Kuileinde"
    }, 
    {
      "hnrlbls": [
        "8"
      ], 
      "housenumber": "8", 
      "lat": 51.316591661559, 
      "lon": 4.97897363222, 
      "municipality": "Oud-Turnhout", 
      "pcode": "2360", 
      "source": "afgeleidVanGebouw", 
      "street": "Kuileinde"
    }, 
    {
      "hnrlbls": [
        "9"
      ], 
      "housenumber": "9", 
      "lat": 51.316534223747, 
      "lon": 4.979305209612, 
      "municipality": "Oud-Turnhout", 
      "pcode": "2360", 
      "source": "afgeleidVanGebouw", 
      "street": "Kuileinde"
    }
  ]
}