{
  "addresses": [
    {
      "busnrs": [
        "0001", 
        "0101", 
        "0102", 
        "0201", 
        "0202", 
        "0203", 
        "0301", 
        "0302", 
        "0401", 
        "0402", 
        "0403", 
        "0501", 
        "0502", 
        "0503", 
        "0601", 
        "0602", 
        "0603", 
        "0701", 
        "0801"
      ], 
      "hnrlbls": [
        "1"
      ], 
      "housenumber": "1", 
      "lat": 51.147695956771, 
      "lon": 2.713404182028, 
      "municipality": "Nieuwpoort", 
      "pcode": "8620", 
      "source": "manueleAanduidingVanGebouw", 
      "street": "Henegouwenstraat"
    }, 
    {
      "busnrs": [
        "-0101", 
        "0001", 
        "0101", 
        "0201", 
        "0301"
      ], 
      "hnrlbls": [
        "10"
      ], 
      "housenumber": "10", 
      "lat": 51.147234878598, 
      "lon": 2.714338926099, 
      "municipality": "Nieuwpoort", 
      "pcode": "8620", 
      "source": "manueleAanduidingVanGebouw", 
      "street": "Henegouwenstraat"
    }, 
    {
      "busnrs": [
        "-0101", 
        "-0102", 
        "0001", 
        "0002", 
        "0101", 
        "0102", 
        "0201", 
        "0202", 
        "0301", 
        "0302", 
        "0401", 
        "0402", 
        "0501"
      ], 
      "hnrlbls": [
        "11"
      ], 
      "housenumber": "11", 
      "lat": 51.147010515066, 
      "lon": 2.714092149577, 
      "municipality": "Nieuwpoort", 
      "pcode": "8620", 
      "source": "manueleAanduidingVanGebouw", 
      "street": "Henegouwenstraat"
    }, 
    {
      "busnrs": [
        "0001"
      ], 
      "hnrlbls": [
        "12"
      ], 
      "housenumber": "12", 
      "lat": 51.147188636114, 
      "lon": 2.714388163584, 
      "municipality": "Nieuwpoort", 
      "pcode": "8620", 
      "source": "manueleAanduidingVanGebouw", 
      "street": "Henegouwenstraat"
    }, 
    {
      "busnrs": [
        "-0101", 
        "-0102", 
        "0001", 
        "0002", 
        "0101", 
        "0102", 
        "0201", 
        "0202", 
        "0301", 
        "0302", 
        "0401", 
        "0402", 
        "0501"
      ], 
      "hnrlbls": [
        "13"
      ], 
      "housenumber": "13", 
      "lat": 51.146929308886, 
      "lon": 2.714180647914, 
      "municipality": "Nieuwpoort", 
      "pcode": "8620", 
      "source": "manueleAanduidingVanGebouw", 
      "street": "Henegouwenstraat"
    }, 
    {
      "busnrs": [
        "0001", 
        "0101", 
        "0201", 
        "0301"
      ], 
      "hnrlbls": [
        "14"
      ], 
      "housenumber": "14", 
      "lat": 51.147146437494, 
      "lon": 2.714437257767, 
      "municipality": "Nieuwpoort", 
      "pcode": "8620", 
      "source": "manueleAanduidingVanGebouw", 
      "street": "Henegouwenstraat"
    }, 
    {
      "busnrs": [
        "0001", 
        "0002", 
        "0101", 
        "0102", 
        "0103", 
        "0104", 
        "0105", 
        "0106", 
        "0107", 
        "0108", 
        "0109", 
        "0110", 
        "0201", 
        "0202", 
        "0203", 
        "0204", 
        "0205", 
        "0206", 
        "0207", 
        "0208", 
        "0209", 
        "0210", 
        "0301", 
        "0302", 
        "0303", 
        "0304", 
        "0305", 
        "0306", 
        "0307", 
        "0308", 
        "0309", 
        "0310", 
        "0401", 
        "0402", 
        "0403", 
        "0404", 
        "0405", 
        "0406", 
        "0407", 
        "0408", 
        "0409", 
        "0410", 
        "0501", 
        "0502", 
        "0503", 
        "0504", 
        "0505", 
        "0506", 
        "0507", 
        "0508", 
        "0509", 
        "0510", 
        "0601", 
        "0602", 
        "0603", 
        "0604", 
        "0605", 
        "0606", 
        "0607", 
        "0608", 
        "0609", 
        "0610", 
        "0701", 
        "0702", 
        "0703", 
        "0704", 
        "0705", 
        "0706", 
        "0707", 
        "0708", 
        "0709", 
        "0710", 
        "0801", 
        "0802", 
        "0803", 
        "0804", 
        "0805", 
        "0806", 
        "0807", 
        "0808", 
        "0809", 
        "0810", 
        "0901", 
        "0902", 
        "0903", 
        "0904", 
        "0905", 
        "0906", 
        "0907", 
        "0908", 
        "0909", 
        "0910", 
        "1001", 
        "1002", 
        "1003", 
        "1004", 
        "1005"
      ], 
      "hnrlbls": [
        "15"
      ], 
      "housenumber": "15", 
      "lat": 51.146445156928, 
      "lon": 2.714495539736, 
      "municipality": "Nieuwpoort", 
      "pcode": "8620", 
      "source": "afgeleidVanGebouw", 
      "street": "Henegouwenstraat"
    }, 
    {
      "busnrs": [
        "0001", 
        "0101", 
        "0102", 
        "0103", 
        "0104", 
        "0105", 
        "0201", 
        "0202", 
        "0203", 
        "0204", 
        "0205", 
        "0301", 
        "0302", 
        "0303", 
        "0304", 
        "0305", 
        "0401", 
        "0402", 
        "0403", 
        "0404", 
        "0405", 
        "0501", 
        "0502", 
        "0503"
      ], 
      "hnrlbls": [
        "16"
      ], 
      "housenumber": "16", 
      "lat": 51.147045906065, 
      "lon": 2.714519721807, 
      "municipality": "Nieuwpoort", 
      "pcode": "8620", 
      "source": "manueleAanduidingVanGebouw", 
      "street": "Henegouwenstraat"
    }, 
    {
      "busnrs": [
        "0001", 
        "0002", 
        "0003", 
        "0101", 
        "0102", 
        "0103", 
        "0104", 
        "0105", 
        "0106", 
        "0201", 
        "0202", 
        "0203", 
        "0204", 
        "0205", 
        "0206", 
        "0301", 
        "0302", 
        "0303", 
        "0304", 
        "0305", 
        "0306", 
        "0401", 
        "0402", 
        "0403", 
        "0404", 
        "0405", 
        "0406", 
        "0501", 
        "0502", 
        "0503", 
        "0504", 
        "0505", 
        "0506", 
        "0601", 
        "0602", 
        "0603", 
        "0604", 
        "0605", 
        "0606", 
        "0701", 
        "0702", 
        "0703", 
        "0704", 
        "0705", 
        "0706", 
        "0801", 
        "0802", 
        "0803", 
        "0804", 
        "0805", 
        "0806", 
        "0901", 
        "0902", 
        "0903", 
        "0904", 
        "0905", 
        "0906", 
        "1002"
      ], 
      "hnrlbls": [
        "17"
      ], 
      "housenumber": "17", 
      "lat": 51.146282588149, 
      "lon": 2.714674253346, 
      "municipality": "Nieuwpoort", 
      "pcode": "8620", 
      "source": "manueleAanduidingVanGebouw", 
      "street": "Henegouwenstraat"
    }, 
    {
      "busnrs": [
        "0101", 
        "0102", 
        "0201", 
        "0202", 
        "0301", 
        "0302", 
        "0303", 
        "0401", 
        "0402", 
        "0501", 
        "0502", 
        "0601", 
        "0602", 
        "0701", 
        "0702", 
        "0801", 
        "0802", 
        "0901"
      ], 
      "hnrlbls": [
        "2"
      ], 
      "housenumber": "2", 
      "lat": 51.147863183399, 
      "lon": 2.713634829347, 
      "municipality": "Nieuwpoort", 
      "pcode": "8620", 
      "source": "manueleAanduidingVanGebouw", 
      "street": "Henegouwenstraat"
    }, 
    {
      "busnrs": [
        "0101", 
        "0102", 
        "0103", 
        "0201", 
        "0202", 
        "0203", 
        "0204", 
        "0205", 
        "0301", 
        "0302", 
        "0303", 
        "0304", 
        "0305", 
        "0401", 
        "0402", 
        "0403", 
        "0404", 
        "0405", 
        "0501", 
        "0502", 
        "0503", 
        "0601", 
        "0701", 
        "0901"
      ], 
      "hnrlbls": [
        "2A"
      ], 
      "housenumber": "2A", 
      "lat": 51.147760117582, 
      "lon": 2.713748119181, 
      "municipality": "Nieuwpoort", 
      "pcode": "8620", 
      "source": "manueleAanduidingVanGebouw", 
      "street": "Henegouwenstraat"
    }, 
    {
      "busnrs": [
        "0101", 
        "0102", 
        "0103", 
        "0104", 
        "0201", 
        "0202", 
        "0203", 
        "0204", 
        "0301", 
        "0302", 
        "0303", 
        "0401", 
        "0402", 
        "0403", 
        "0404", 
        "0501", 
        "0502", 
        "0503", 
        "0504", 
        "0601", 
        "0602", 
        "0603"
      ], 
      "hnrlbls": [
        "4"
      ], 
      "housenumber": "4", 
      "lat": 51.147371547258, 
      "lon": 2.714140541231, 
      "municipality": "Nieuwpoort", 
      "pcode": "8620", 
      "source": "manueleAanduidingVanGebouw", 
      "street": "Henegouwenstraat"
    }, 
    {
      "apptnrs": [
        "0301"
      ], 
      "busnrs": [
        "0001", 
        "0101", 
        "0201"
      ], 
      "hnrlbls": [
        "5"
      ], 
      "housenumber": "5", 
      "lat": 51.147524901464, 
      "lon": 2.71360593298, 
      "municipality": "Nieuwpoort", 
      "pcode": "8620", 
      "source": "manueleAanduidingVanGebouw", 
      "street": "Henegouwenstraat"
    }, 
    {
      "busnrs": [
        "0001", 
        "0101", 
        "0201", 
        "0301", 
        "0401", 
        "0501", 
        "0601"
      ], 
      "hnrlbls": [
        "6"
      ], 
      "housenumber": "6", 
      "lat": 51.147310329361, 
      "lon": 2.714243912992, 
      "municipality": "Nieuwpoort", 
      "pcode": "8620", 
      "source": "manueleAanduidingVanGebouw", 
      "street": "Henegouwenstraat"
    }, 
    {
      "busnrs": [
        "0001", 
        "0101", 
        "0201"
      ], 
      "hnrlbls": [
        "8"
      ], 
      "housenumber": "8", 
      "lat": 51.147270269524, 
      "lon": 2.714291645204, 
      "municipality": "Nieuwpoort", 
      "pcode": "8620", 
      "source": "manueleAanduidingVanGebouw", 
      "street": "Henegouwenstraat"
    }, 
    {
      "busnrs": [
        "-0101", 
        "-0102", 
        "0001", 
        "0002", 
        "0003", 
        "0101", 
        "0102", 
        "0201", 
        "0202", 
        "0301", 
        "0302", 
        "0401", 
        "0402", 
        "0501"
      ], 
      "hnrlbls": [
        "9"
      ], 
      "housenumber": "9", 
      "lat": 51.147092779525, 
      "lon": 2.714002184021, 
      "municipality": "Nieuwpoort", 
      "pcode": "8620", 
      "source": "manueleAanduidingVanGebouw", 
      "street": "Henegouwenstraat"
    }
  ]
}