{
  "addresses": [
    {
      "hnrlbls": [
        "1"
      ], 
      "housenumber": "1", 
      "lat": 50.799369364184, 
      "lon": 3.194105329901, 
      "municipality": "Menen", 
      "pcode": "8930", 
      "source": "manueleAanduidingVanGebouw", 
      "street": "Oudstrijderslaan"
    }, 
    {
      "hnrlbls": [
        "10"
      ], 
      "housenumber": "10", 
      "lat": 50.799193202888, 
      "lon": 3.194416159446, 
      "municipality": "Menen", 
      "pcode": "8930", 
      "source": "manueleAanduidingVanGebouw", 
      "street": "Oudstrijderslaan"
    }, 
    {
      "hnrlbls": [
        "12"
      ], 
      "housenumber": "12", 
      "lat": 50.799215116809, 
      "lon": 3.194539463427, 
      "municipality": "Menen", 
      "pcode": "8930", 
      "source": "manueleAanduidingVanGebouw", 
      "street": "Oudstrijderslaan"
    }, 
    {
      "hnrlbls": [
        "13-13A"
      ], 
      "housenumber": "13", 
      "lat": 50.800097120569, 
      "lon": 3.194441848179, 
      "municipality": "Menen", 
      "pcode": "8930", 
      "source": "manueleAanduidingVanGebouw", 
      "street": "Oudstrijderslaan"
    }, 
    {
      "hnrlbls": [
        "13-13A"
      ], 
      "housenumber": "13A", 
      "lat": 50.800097120569, 
      "lon": 3.194441848179, 
      "municipality": "Menen", 
      "pcode": "8930", 
      "source": "manueleAanduidingVanGebouw", 
      "street": "Oudstrijderslaan"
    }, 
    {
      "hnrlbls": [
        "14"
      ], 
      "housenumber": "14", 
      "lat": 50.79895429441, 
      "lon": 3.194584272603, 
      "municipality": "Menen", 
      "pcode": "8930", 
      "source": "manueleAanduidingVanGebouw", 
      "street": "Oudstrijderslaan"
    }, 
    {
      "hnrlbls": [
        "14A"
      ], 
      "housenumber": "14A", 
      "lat": 50.798886610573, 
      "lon": 3.194594898224, 
      "municipality": "Menen", 
      "pcode": "8930", 
      "source": "manueleAanduidingVanGebouw", 
      "street": "Oudstrijderslaan"
    }, 
    {
      "hnrlbls": [
        "15"
      ], 
      "housenumber": "15", 
      "lat": 50.800190572587, 
      "lon": 3.194436679754, 
      "municipality": "Menen", 
      "pcode": "8930", 
      "source": "manueleAanduidingVanGebouw", 
      "street": "Oudstrijderslaan"
    }, 
    {
      "hnrlbls": [
        "16"
      ], 
      "housenumber": "16", 
      "lat": 50.798716928704, 
      "lon": 3.194538411206, 
      "municipality": "Menen", 
      "pcode": "8930", 
      "source": "manueleAanduidingVanGebouw", 
      "street": "Oudstrijderslaan"
    }, 
    {
      "hnrlbls": [
        "17"
      ], 
      "housenumber": "17", 
      "lat": 50.800317580711, 
      "lon": 3.194622058438, 
      "municipality": "Menen", 
      "pcode": "8930", 
      "source": "manueleAanduidingVanGebouw", 
      "street": "Oudstrijderslaan"
    }, 
    {
      "hnrlbls": [
        "18"
      ], 
      "housenumber": "18", 
      "lat": 50.798504845562, 
      "lon": 3.194611086839, 
      "municipality": "Menen", 
      "pcode": "8930", 
      "source": "manueleAanduidingVanGebouw", 
      "street": "Oudstrijderslaan"
    }, 
    {
      "hnrlbls": [
        "19"
      ], 
      "housenumber": "19", 
      "lat": 50.80033152171, 
      "lon": 3.194873957672, 
      "municipality": "Menen", 
      "pcode": "8930", 
      "source": "manueleAanduidingVanGebouw", 
      "street": "Oudstrijderslaan"
    }, 
    {
      "hnrlbls": [
        "2"
      ], 
      "housenumber": "2", 
      "lat": 50.799094315958, 
      "lon": 3.193807177325, 
      "municipality": "Menen", 
      "pcode": "8930", 
      "source": "manueleAanduidingVanGebouw", 
      "street": "Oudstrijderslaan"
    }, 
    {
      "hnrlbls": [
        "20"
      ], 
      "housenumber": "20", 
      "lat": 50.798595531, 
      "lon": 3.194868298014, 
      "municipality": "Menen", 
      "pcode": "8930", 
      "source": "manueleAanduidingVanGebouw", 
      "street": "Oudstrijderslaan"
    }, 
    {
      "hnrlbls": [
        "21"
      ], 
      "housenumber": "21", 
      "lat": 50.800344843908, 
      "lon": 3.195135945321, 
      "municipality": "Menen", 
      "pcode": "8930", 
      "source": "manueleAanduidingVanGebouw", 
      "street": "Oudstrijderslaan"
    }, 
    {
      "hnrlbls": [
        "22"
      ], 
      "housenumber": "22", 
      "lat": 50.798580892946, 
      "lon": 3.195256098682, 
      "municipality": "Menen", 
      "pcode": "8930", 
      "source": "manueleAanduidingVanGebouw", 
      "street": "Oudstrijderslaan"
    }, 
    {
      "hnrlbls": [
        "23"
      ], 
      "housenumber": "23", 
      "lat": 50.800358626214, 
      "lon": 3.195372101075, 
      "municipality": "Menen", 
      "pcode": "8930", 
      "source": "manueleAanduidingVanGebouw", 
      "street": "Oudstrijderslaan"
    }, 
    {
      "hnrlbls": [
        "24"
      ], 
      "housenumber": "24", 
      "lat": 50.798764002917, 
      "lon": 3.195046395765, 
      "municipality": "Menen", 
      "pcode": "8930", 
      "source": "manueleAanduidingVanGebouw", 
      "street": "Oudstrijderslaan"
    }, 
    {
      "hnrlbls": [
        "25"
      ], 
      "housenumber": "25", 
      "lat": 50.800382049414, 
      "lon": 3.19561936642, 
      "municipality": "Menen", 
      "pcode": "8930", 
      "source": "manueleAanduidingVanGebouw", 
      "street": "Oudstrijderslaan"
    }, 
    {
      "hnrlbls": [
        "26"
      ], 
      "housenumber": "26", 
      "lat": 50.798847359881, 
      "lon": 3.195029705423, 
      "municipality": "Menen", 
      "pcode": "8930", 
      "source": "manueleAanduidingVanGebouw", 
      "street": "Oudstrijderslaan"
    }, 
    {
      "hnrlbls": [
        "27"
      ], 
      "housenumber": "27", 
      "lat": 50.800442628652, 
      "lon": 3.195896066813, 
      "municipality": "Menen", 
      "pcode": "8930", 
      "source": "manueleAanduidingVanGebouw", 
      "street": "Oudstrijderslaan"
    }, 
    {
      "hnrlbls": [
        "28"
      ], 
      "housenumber": "28", 
      "lat": 50.798932075057, 
      "lon": 3.195013974229, 
      "municipality": "Menen", 
      "pcode": "8930", 
      "source": "manueleAanduidingVanGebouw", 
      "street": "Oudstrijderslaan"
    }, 
    {
      "hnrlbls": [
        "29"
      ], 
      "housenumber": "29", 
      "lat": 50.800300479788, 
      "lon": 3.196093262053, 
      "municipality": "Menen", 
      "pcode": "8930", 
      "source": "manueleAanduidingVanGebouw", 
      "street": "Oudstrijderslaan"
    }, 
    {
      "hnrlbls": [
        "3"
      ], 
      "housenumber": "3", 
      "lat": 50.799392862964, 
      "lon": 3.194243207108, 
      "municipality": "Menen", 
      "pcode": "8930", 
      "source": "manueleAanduidingVanGebouw", 
      "street": "Oudstrijderslaan"
    }, 
    {
      "hnrlbls": [
        "30"
      ], 
      "housenumber": "30", 
      "lat": 50.799027075473, 
      "lon": 3.195001816973, 
      "municipality": "Menen", 
      "pcode": "8930", 
      "source": "manueleAanduidingVanGebouw", 
      "street": "Oudstrijderslaan"
    }, 
    {
      "hnrlbls": [
        "31"
      ], 
      "housenumber": "31", 
      "lat": 50.800124048318, 
      "lon": 3.196045022701, 
      "municipality": "Menen", 
      "pcode": "8930", 
      "source": "manueleAanduidingVanGebouw", 
      "street": "Oudstrijderslaan"
    }, 
    {
      "hnrlbls": [
        "33"
      ], 
      "housenumber": "33", 
      "lat": 50.799951973322, 
      "lon": 3.196036824392, 
      "municipality": "Menen", 
      "pcode": "8930", 
      "source": "manueleAanduidingVanGebouw", 
      "street": "Oudstrijderslaan"
    }, 
    {
      "hnrlbls": [
        "34"
      ], 
      "housenumber": "34", 
      "lat": 50.799298816307, 
      "lon": 3.19512258156, 
      "municipality": "Menen", 
      "pcode": "8930", 
      "source": "manueleAanduidingVanGebouw", 
      "street": "Oudstrijderslaan"
    }, 
    {
      "hnrlbls": [
        "35"
      ], 
      "housenumber": "35", 
      "lat": 50.799765421012, 
      "lon": 3.196082329664, 
      "municipality": "Menen", 
      "pcode": "8930", 
      "source": "manueleAanduidingVanGebouw", 
      "street": "Oudstrijderslaan"
    }, 
    {
      "hnrlbls": [
        "37"
      ], 
      "housenumber": "37", 
      "lat": 50.799764890623, 
      "lon": 3.19570582145, 
      "municipality": "Menen", 
      "pcode": "8930", 
      "source": "manueleAanduidingVanGebouw", 
      "street": "Oudstrijderslaan"
    }, 
    {
      "hnrlbls": [
        "38"
      ], 
      "housenumber": "38", 
      "lat": 50.799352137785, 
      "lon": 3.195392646183, 
      "municipality": "Menen", 
      "pcode": "8930", 
      "source": "manueleAanduidingVanGebouw", 
      "street": "Oudstrijderslaan"
    }, 
    {
      "hnrlbls": [
        "39"
      ], 
      "housenumber": "39", 
      "lat": 50.799939525464, 
      "lon": 3.195682317736, 
      "municipality": "Menen", 
      "pcode": "8930", 
      "source": "manueleAanduidingVanGebouw", 
      "street": "Oudstrijderslaan"
    }, 
    {
      "hnrlbls": [
        "4"
      ], 
      "housenumber": "4", 
      "lat": 50.79911393824, 
      "lon": 3.19391706055, 
      "municipality": "Menen", 
      "pcode": "8930", 
      "source": "manueleAanduidingVanGebouw", 
      "street": "Oudstrijderslaan"
    }, 
    {
      "hnrlbls": [
        "40"
      ], 
      "housenumber": "40", 
      "lat": 50.799409191278, 
      "lon": 3.195739227318, 
      "municipality": "Menen", 
      "pcode": "8930", 
      "source": "manueleAanduidingVanGebouw", 
      "street": "Oudstrijderslaan"
    }, 
    {
      "hnrlbls": [
        "41"
      ], 
      "housenumber": "41", 
      "lat": 50.8001405646, 
      "lon": 3.195557144084, 
      "municipality": "Menen", 
      "pcode": "8930", 
      "source": "manueleAanduidingVanGebouw", 
      "street": "Oudstrijderslaan"
    }, 
    {
      "hnrlbls": [
        "42"
      ], 
      "housenumber": "42", 
      "lat": 50.799139829792, 
      "lon": 3.195856169601, 
      "municipality": "Menen", 
      "pcode": "8930", 
      "source": "manueleAanduidingVanGebouw", 
      "street": "Oudstrijderslaan"
    }, 
    {
      "hnrlbls": [
        "44"
      ], 
      "housenumber": "44", 
      "lat": 50.798962344141, 
      "lon": 3.195828387436, 
      "municipality": "Menen", 
      "pcode": "8930", 
      "source": "manueleAanduidingVanGebouw", 
      "street": "Oudstrijderslaan"
    }, 
    {
      "hnrlbls": [
        "45"
      ], 
      "housenumber": "45", 
      "lat": 50.800074988982, 
      "lon": 3.194835381187, 
      "municipality": "Menen", 
      "pcode": "8930", 
      "source": "manueleAanduidingVanGebouw", 
      "street": "Oudstrijderslaan"
    }, 
    {
      "hnrlbls": [
        "46"
      ], 
      "housenumber": "46", 
      "lat": 50.798816391586, 
      "lon": 3.195789179879, 
      "municipality": "Menen", 
      "pcode": "8930", 
      "source": "manueleAanduidingVanGebouw", 
      "street": "Oudstrijderslaan"
    }, 
    {
      "hnrlbls": [
        "47"
      ], 
      "housenumber": "47", 
      "lat": 50.800001563862, 
      "lon": 3.194847284818, 
      "municipality": "Menen", 
      "pcode": "8930", 
      "source": "manueleAanduidingVanGebouw", 
      "street": "Oudstrijderslaan"
    }, 
    {
      "hnrlbls": [
        "48"
      ], 
      "housenumber": "48", 
      "lat": 50.79869558317, 
      "lon": 3.196106423302, 
      "municipality": "Menen", 
      "pcode": "8930", 
      "source": "manueleAanduidingVanGebouw", 
      "street": "Oudstrijderslaan"
    }, 
    {
      "hnrlbls": [
        "49"
      ], 
      "housenumber": "49", 
      "lat": 50.799856743431, 
      "lon": 3.194912183578, 
      "municipality": "Menen", 
      "pcode": "8930", 
      "source": "manueleAanduidingVanGebouw", 
      "street": "Oudstrijderslaan"
    }, 
    {
      "hnrlbls": [
        "5"
      ], 
      "housenumber": "5", 
      "lat": 50.799513883262, 
      "lon": 3.194566769736, 
      "municipality": "Menen", 
      "pcode": "8930", 
      "source": "manueleAanduidingVanGebouw", 
      "street": "Oudstrijderslaan"
    }, 
    {
      "hnrlbls": [
        "50"
      ], 
      "housenumber": "50", 
      "lat": 50.798686173933, 
      "lon": 3.196379182537, 
      "municipality": "Menen", 
      "pcode": "8930", 
      "source": "manueleAanduidingVanGebouw", 
      "street": "Oudstrijderslaan"
    }, 
    {
      "hnrlbls": [
        "51"
      ], 
      "housenumber": "51", 
      "lat": 50.799767800452, 
      "lon": 3.194873826545, 
      "municipality": "Menen", 
      "pcode": "8930", 
      "source": "manueleAanduidingVanGebouw", 
      "street": "Oudstrijderslaan"
    }, 
    {
      "hnrlbls": [
        "52"
      ], 
      "housenumber": "52", 
      "lat": 50.798851351295, 
      "lon": 3.19632697658, 
      "municipality": "Menen", 
      "pcode": "8930", 
      "source": "manueleAanduidingVanGebouw", 
      "street": "Oudstrijderslaan"
    }, 
    {
      "hnrlbls": [
        "53"
      ], 
      "housenumber": "53", 
      "lat": 50.799613940575, 
      "lon": 3.194897950138, 
      "municipality": "Menen", 
      "pcode": "8930", 
      "source": "manueleAanduidingVanGebouw", 
      "street": "Oudstrijderslaan"
    }, 
    {
      "hnrlbls": [
        "54"
      ], 
      "housenumber": "54", 
      "lat": 50.798931090338, 
      "lon": 3.196308108707, 
      "municipality": "Menen", 
      "pcode": "8930", 
      "source": "manueleAanduidingVanGebouw", 
      "street": "Oudstrijderslaan"
    }, 
    {
      "hnrlbls": [
        "55"
      ], 
      "housenumber": "55", 
      "lat": 50.799539206931, 
      "lon": 3.194913858506, 
      "municipality": "Menen", 
      "pcode": "8930", 
      "source": "manueleAanduidingVanGebouw", 
      "street": "Oudstrijderslaan"
    }, 
    {
      "hnrlbls": [
        "56"
      ], 
      "housenumber": "56", 
      "lat": 50.799014323547, 
      "lon": 3.196288018816, 
      "municipality": "Menen", 
      "pcode": "8930", 
      "source": "manueleAanduidingVanGebouw", 
      "street": "Oudstrijderslaan"
    }, 
    {
      "hnrlbls": [
        "58"
      ], 
      "housenumber": "58", 
      "lat": 50.799094096627, 
      "lon": 3.196272554781, 
      "municipality": "Menen", 
      "pcode": "8930", 
      "source": "manueleAanduidingVanGebouw", 
      "street": "Oudstrijderslaan"
    }, 
    {
      "hnrlbls": [
        "6"
      ], 
      "housenumber": "6", 
      "lat": 50.799152846065, 
      "lon": 3.1941660604, 
      "municipality": "Menen", 
      "pcode": "8930", 
      "source": "manueleAanduidingVanGebouw", 
      "street": "Oudstrijderslaan"
    }, 
    {
      "hnrlbls": [
        "60"
      ], 
      "housenumber": "60", 
      "lat": 50.799183351499, 
      "lon": 3.196288207306, 
      "municipality": "Menen", 
      "pcode": "8930", 
      "source": "afgeleidVanGebouw", 
      "street": "Oudstrijderslaan"
    }, 
    {
      "hnrlbls": [
        "61"
      ], 
      "housenumber": "61", 
      "lat": 50.799673620389, 
      "lon": 3.195731362101, 
      "municipality": "Menen", 
      "pcode": "8930", 
      "source": "manueleAanduidingVanGebouw", 
      "street": "Oudstrijderslaan"
    }, 
    {
      "hnrlbls": [
        "63"
      ], 
      "housenumber": "63", 
      "lat": 50.799773047586, 
      "lon": 3.196494270383, 
      "municipality": "Menen", 
      "pcode": "8930", 
      "source": "manueleAanduidingVanGebouw", 
      "street": "Oudstrijderslaan"
    }, 
    {
      "hnrlbls": [
        "64"
      ], 
      "housenumber": "64", 
      "lat": 50.799267270047, 
      "lon": 3.196183830669, 
      "municipality": "Menen", 
      "pcode": "8930", 
      "source": "manueleAanduidingVanGebouw", 
      "street": "Oudstrijderslaan"
    }, 
    {
      "hnrlbls": [
        "65"
      ], 
      "housenumber": "65", 
      "lat": 50.799487954451, 
      "lon": 3.196188974448, 
      "municipality": "Menen", 
      "pcode": "8930", 
      "source": "manueleAanduidingVanGebouw", 
      "street": "Oudstrijderslaan"
    }, 
    {
      "hnrlbls": [
        "66"
      ], 
      "housenumber": "66", 
      "lat": 50.799509923248, 
      "lon": 3.196317953359, 
      "municipality": "Menen", 
      "pcode": "8930", 
      "source": "manueleAanduidingVanGebouw", 
      "street": "Oudstrijderslaan"
    }, 
    {
      "hnrlbls": [
        "68"
      ], 
      "housenumber": "68", 
      "lat": 50.799553843295, 
      "lon": 3.196924909098, 
      "municipality": "Menen", 
      "pcode": "8930", 
      "source": "manueleAanduidingVanGebouw", 
      "street": "Oudstrijderslaan"
    }, 
    {
      "hnrlbls": [
        "7"
      ], 
      "housenumber": "7", 
      "lat": 50.799715392852, 
      "lon": 3.194524574231, 
      "municipality": "Menen", 
      "pcode": "8930", 
      "source": "manueleAanduidingVanGebouw", 
      "street": "Oudstrijderslaan"
    }, 
    {
      "hnrlbls": [
        "8"
      ], 
      "housenumber": "8", 
      "lat": 50.799174018432, 
      "lon": 3.194287112781, 
      "municipality": "Menen", 
      "pcode": "8930", 
      "source": "manueleAanduidingVanGebouw", 
      "street": "Oudstrijderslaan"
    }, 
    {
      "hnrlbls": [
        "9"
      ], 
      "housenumber": "9", 
      "lat": 50.799885864998, 
      "lon": 3.194516350049, 
      "municipality": "Menen", 
      "pcode": "8930", 
      "source": "manueleAanduidingVanGebouw", 
      "street": "Oudstrijderslaan"
    }
  ]
}