{
  "addresses": [
    {
      "hnrlbls": [
        "1"
      ], 
      "housenumber": "1", 
      "lat": 51.03321530269, 
      "lon": 3.031815968083, 
      "municipality": "Kortemark", 
      "pcode": "8610", 
      "source": "afgeleidVanGebouw", 
      "street": "Schreveweg"
    }, 
    {
      "hnrlbls": [
        "11"
      ], 
      "housenumber": "11", 
      "lat": 51.032961336156, 
      "lon": 3.031096480076, 
      "municipality": "Kortemark", 
      "pcode": "8610", 
      "source": "afgeleidVanGebouw", 
      "street": "Schreveweg"
    }, 
    {
      "hnrlbls": [
        "13"
      ], 
      "housenumber": "13", 
      "lat": 51.032999075736, 
      "lon": 3.031213459731, 
      "municipality": "Kortemark", 
      "pcode": "8610", 
      "source": "afgeleidVanGebouw", 
      "street": "Schreveweg"
    }, 
    {
      "hnrlbls": [
        "15"
      ], 
      "housenumber": "15", 
      "lat": 51.033037764858, 
      "lon": 3.031342817055, 
      "municipality": "Kortemark", 
      "pcode": "8610", 
      "source": "afgeleidVanGebouw", 
      "street": "Schreveweg"
    }, 
    {
      "hnrlbls": [
        "17"
      ], 
      "housenumber": "17", 
      "lat": 51.033084175615, 
      "lon": 3.031495052367, 
      "municipality": "Kortemark", 
      "pcode": "8610", 
      "source": "afgeleidVanGebouw", 
      "street": "Schreveweg"
    }, 
    {
      "hnrlbls": [
        "3"
      ], 
      "housenumber": "3", 
      "lat": 51.033061370479, 
      "lon": 3.031933429103, 
      "municipality": "Kortemark", 
      "pcode": "8610", 
      "source": "afgeleidVanGebouw", 
      "street": "Schreveweg"
    }, 
    {
      "hnrlbls": [
        "5"
      ], 
      "housenumber": "5", 
      "lat": 51.032741664604, 
      "lon": 3.031188444624, 
      "municipality": "Kortemark", 
      "pcode": "8610", 
      "source": "afgeleidVanGebouw", 
      "street": "Schreveweg"
    }, 
    {
      "hnrlbls": [
        "7"
      ], 
      "housenumber": "7", 
      "lat": 51.032716897297, 
      "lon": 3.030867917773, 
      "municipality": "Kortemark", 
      "pcode": "8610", 
      "source": "afgeleidVanGebouw", 
      "street": "Schreveweg"
    }, 
    {
      "hnrlbls": [
        "9"
      ], 
      "housenumber": "9", 
      "lat": 51.032782761691, 
      "lon": 3.030801447328, 
      "municipality": "Kortemark", 
      "pcode": "8610", 
      "source": "afgeleidVanGebouw", 
      "street": "Schreveweg"
    }
  ]
}