{
  "addresses": [
    {
      "hnrlbls": [
        "1"
      ], 
      "housenumber": "1", 
      "lat": 50.968492333838, 
      "lon": 3.511417612507, 
      "municipality": "Deinze", 
      "pcode": "9800", 
      "source": "afgeleidVanGebouw", 
      "street": "Watertorenstraat"
    }, 
    {
      "hnrlbls": [
        "10"
      ], 
      "housenumber": "10", 
      "lat": 50.968312256859, 
      "lon": 3.511601144737, 
      "municipality": "Deinze", 
      "pcode": "9800", 
      "source": "afgeleidVanGebouw", 
      "street": "Watertorenstraat"
    }, 
    {
      "hnrlbls": [
        "11"
      ], 
      "housenumber": "11", 
      "lat": 50.968365499203, 
      "lon": 3.511678333941, 
      "municipality": "Deinze", 
      "pcode": "9800", 
      "source": "afgeleidVanGebouw", 
      "street": "Watertorenstraat"
    }, 
    {
      "hnrlbls": [
        "2"
      ], 
      "housenumber": "2", 
      "lat": 50.968436206332, 
      "lon": 3.511363967411, 
      "municipality": "Deinze", 
      "pcode": "9800", 
      "source": "afgeleidVanGebouw", 
      "street": "Watertorenstraat"
    }, 
    {
      "hnrlbls": [
        "3"
      ], 
      "housenumber": "3", 
      "lat": 50.968361244346, 
      "lon": 3.511106648567, 
      "municipality": "Deinze", 
      "pcode": "9800", 
      "source": "afgeleidVanGebouw", 
      "street": "Watertorenstraat"
    }, 
    {
      "hnrlbls": [
        "4"
      ], 
      "housenumber": "4", 
      "lat": 50.968296301366, 
      "lon": 3.511076941109, 
      "municipality": "Deinze", 
      "pcode": "9800", 
      "source": "afgeleidVanGebouw", 
      "street": "Watertorenstraat"
    }, 
    {
      "hnrlbls": [
        "5"
      ], 
      "housenumber": "5", 
      "lat": 50.968233110723, 
      "lon": 3.511016307213, 
      "municipality": "Deinze", 
      "pcode": "9800", 
      "source": "afgeleidVanGebouw", 
      "street": "Watertorenstraat"
    }, 
    {
      "hnrlbls": [
        "6"
      ], 
      "housenumber": "6", 
      "lat": 50.968186871779, 
      "lon": 3.510937994338, 
      "municipality": "Deinze", 
      "pcode": "9800", 
      "source": "afgeleidVanGebouw", 
      "street": "Watertorenstraat"
    }, 
    {
      "hnrlbls": [
        "7"
      ], 
      "housenumber": "7", 
      "lat": 50.968205684259, 
      "lon": 3.510546700103, 
      "municipality": "Deinze", 
      "pcode": "9800", 
      "source": "afgeleidVanGebouw", 
      "street": "Watertorenstraat"
    }, 
    {
      "hnrlbls": [
        "8"
      ], 
      "housenumber": "8", 
      "lat": 50.968092391617, 
      "lon": 3.510395866374, 
      "municipality": "Deinze", 
      "pcode": "9800", 
      "source": "afgeleidVanPerceelGrb", 
      "street": "Watertorenstraat"
    }, 
    {
      "hnrlbls": [
        "9"
      ], 
      "housenumber": "9", 
      "lat": 50.968256028141, 
      "lon": 3.511545935397, 
      "municipality": "Deinze", 
      "pcode": "9800", 
      "source": "afgeleidVanGebouw", 
      "street": "Watertorenstraat"
    }
  ]
}